Metadata-Version: 2.1
Name: lantern-smt
Version: 0.1.0
Summary: Tools to encode PyTorch modules as Z3 constraints
Home-page: https://github.com/JHUAPL/lantern-smt
Author: Joshua Brule
Author-email: joshua.brule@jhuapl.edu
License: 3-Clause BSD License
Platform: UNKNOWN
Requires-Python: >=3
